WinForm/Main.py
WinForm/__init__.py
WinForm/CommonObject/Build.py
WinForm/CommonObject/InputObject.py
WinForm/CommonObject/MessageLogger.py
WinForm/CommonObject/TmpFile.py
WinForm/CommonObject/__init__.py
WinForm/DataProcess/AnswerSave.py
WinForm/DataProcess/PictureProcess.py
WinForm/DataProcess/ProcessMain.py
WinForm/DataProcess/ResTransformerPredict.py
WinForm/DataProcess/SedProcess.py
WinForm/DataProcess/__init__.py
WinForm/Form/InteractiveScene.py
WinForm/Form/MainWindow.py
WinForm/Form/MessageBoxes.py
WinForm/Form/WindowEvent.py
WinForm/Form/__init__.py
WinForm/ScaleConvertion/SC.py
WinForm/ScaleConvertion/__init__.py
WinForm/ScaleConvertion/Model/Efficientnet.py
WinForm/ScaleConvertion/Model/Restnet.py
WinForm/ScaleConvertion/Model/SwimModel.py
WinForm/ScaleConvertion/Model/SwimModel_2.py
WinForm/ScaleConvertion/Model/__init__.py
WinForm/ScaleConvertion/Model/restnet_transformer.py
WinForm/ScaleConvertion/PicProcess/ConcatAnswer.py
WinForm/ScaleConvertion/PicProcess/DataPredict.py
WinForm/ScaleConvertion/PicProcess/Draw_Window.py
WinForm/ScaleConvertion/PicProcess/MakeData.py
WinForm/ScaleConvertion/PicProcess/__init__.py
WinForm/ScaleConvertion/PicProcess/save4_0.003732832917032445mt.pth
WinForm/ScaleConvertion/Utiles/Info.py
WinForm/ScaleConvertion/Utiles/PictureInfo.py
WinForm/ScaleConvertion/Utiles/SED.py
WinForm/ScaleConvertion/Utiles/SaveFile.py
WinForm/ScaleConvertion/Utiles/ScaleCompute.py
WinForm/ScaleConvertion/Utiles/__init__.py
WinForm/ScaleConvertion/test/__init__.py
WinForm/ScaleConvertion/test/test.py
WinForm/ScaleConvertion/test/testuav.py
ScaleConvertionTools-0.3.dist-info/LICENSE
ScaleConvertionTools-0.3.dist-info/METADATA
ScaleConvertionTools-0.3.dist-info/WHEEL
ScaleConvertionTools-0.3.dist-info/entry_points.txt
ScaleConvertionTools-0.3.dist-info/top_level.txt
ScaleConvertionTools-0.3.dist-info/RECORD
