Metadata-Version: 2.1
Name: ScaleConvertionTools
Version: 0.3
Summary: Helps achieve surface reflectance scale conversion
Home-page: https://github.com/qxcnwu
Author: qxcnwu
Author-email: qxcnwu@gmail.com
Maintainer: qxcnwu
Maintainer-email: qxcnwu@gmail.com
License: MIT License
Classifier: Development Status :: 3 - Alpha
Classifier: Intended Audience :: Developers
Classifier: Topic :: Software Development :: Build Tools
Classifier: License :: OSI Approved :: MIT License
Classifier: Programming Language :: Python :: 3
Requires-Python: >=3.6
License-File: LICENSE
Requires-Dist: numpy
Requires-Dist: pandas
Requires-Dist: torch
Requires-Dist: matplotlib
Requires-Dist: torchvision
Requires-Dist: ScaleConvertion
Requires-Dist: opencv-python
Requires-Dist: PyQt5
